perflog/__init__.py
perflog/async.py
perflog-2017.8.7.dist-info/LICENSE
perflog-2017.8.7.dist-info/WHEEL
perflog-2017.8.7.dist-info/METADATA
perflog-2017.8.7.dist-info/RECORD
